see/__init__.py
see/environment.py
see/events.py
see/helpers.py
see/hooks.py
see/interfaces.py
see/observer.py
see/context/__init__.py
see/context/context.py
see/context/resources/__init__.py
see/context/resources/helpers.py
see/context/resources/lxc.py
see/context/resources/network.py
see/context/resources/qemu.py
see/context/resources/resources.py
see/context/resources/vbox.py
see/image_providers/__init__.py
see/image_providers/dummy.py
see/image_providers/helpers.py
see/image_providers/libvirt_pool.py
see/image_providers/os_glance.py
see/image_providers/s3.py
see/test/__init__.py
see/test/environment_test.py
see/test/events_test.py
see/test/hooks_manager_test.py
python_see-1.3.7.dist-info/LICENSE.txt
python_see-1.3.7.dist-info/METADATA
python_see-1.3.7.dist-info/WHEEL
python_see-1.3.7.dist-info/top_level.txt
python_see-1.3.7.dist-info/RECORD
