Metadata-Version: 2.1
Name: python-see
Version: 1.3.7
Summary: Sandboxed Execution Environment
Home-page: https://github.com/f-secure/see
Author: F-Secure Corporation
Author-email: matteo.cafasso@f-secure.com
License: Apache License 2.0
Keywords: sandbox test automation
Platform: UNKNOWN
Classifier: Programming Language :: Python
Classifier: Programming Language :: Python :: 3
Classifier: Development Status :: 5 - Production/Stable
Classifier: License :: OSI Approved :: Apache Software License
Classifier: Topic :: Software Development :: Libraries :: Python Modules
Requires-Dist: libvirt-python
